graphene_sqlalchemy_auto/__init__.py
graphene_sqlalchemy_auto/filter.py
graphene_sqlalchemy_auto/mutation.py
graphene_sqlalchemy_auto/query.py
graphene_sqlalchemy_auto/types.py
graphene_sqlalchemy_auto-1.5.0.dist-info/LICENSE
graphene_sqlalchemy_auto-1.5.0.dist-info/METADATA
graphene_sqlalchemy_auto-1.5.0.dist-info/WHEEL
graphene_sqlalchemy_auto-1.5.0.dist-info/top_level.txt
graphene_sqlalchemy_auto-1.5.0.dist-info/RECORD
