Metadata-Version: 2.1
Name: graphene-sqlalchemy-auto
Version: 1.5.0
Summary: generate default graphene schema from sqlalchemy model base on graphene-sqlalchemy
Home-page: https://github.com/goodking-bq/graphene-sqlalchemy-auto.git
Author: golsee
Author-email: z.shj726@gmail.com
License: UNKNOWN
Platform: UNKNOWN
Classifier: Intended Audience :: Developers
Classifier: Topic :: Software Development :: Libraries
Classifier: Programming Language :: Python :: 3
Classifier: Programming Language :: Python :: 3.6
Classifier: Programming Language :: Python :: 3.7
Classifier: Programming Language :: Python :: 3.8
Classifier: License :: OSI Approved :: MIT License
Classifier: Operating System :: OS Independent
Requires-Python: >=3.6
License-File: LICENSE
